README.md
setup.py
ft_jwt/__init__.py
ft_jwt/ft_jwt.py
ft_jwt.egg-info/PKG-INFO
ft_jwt.egg-info/SOURCES.txt
ft_jwt.egg-info/dependency_links.txt
ft_jwt.egg-info/top_level.txt