Metadata-Version: 2.1
Name: ft-jwt
Version: 0.1.0
Summary: A Python implementation of JSON Web Tokens (JWT) for authentication and authorization using a symmetric secret key and HMAC-SHA256.
Home-page: https://github.com/minthe/ft_transcendence/blob/main/auth/ft_jwt/ft_jwt/ft_jwt.py
Author: vfuhlenb
Author-email: minh.tee@gmail.com
License: UNKNOWN
Platform: UNKNOWN
Classifier: Programming Language :: Python :: 3
Classifier: License :: OSI Approved :: MIT License
Classifier: Operating System :: OS Independent
Requires-Python: >=3.6
